twkorean
