Metadata-Version: 1.1
Name: twkorean
Version: 0.1.3
Summary: Python interface to twitter-korean-text, a Korean morphological analyzer.
Home-page: https://github.com/jaepil/twkorean/
Author: Jaepil Jeong
Author-email: jaepil@{nospam}appspand.com
License: Apache 2.0
Download-URL: https://github.com/jaepil/twkorean/tree/master
Keywords: twitter-korean-text,morphological analyzer,morphology,analyzerkorean,tokenizer
Platform: Operating System :: MacOS :: MacOS X
Platform: Operating System :: Microsoft :: Windows :: Windows 7
Platform: Operating System :: Microsoft :: Windows :: Windows Vista
Platform: Operating System :: POSIX :: Linux
Classifier: Programming Language :: Java
Classifier: Programming Language :: Python :: 2.6
Classifier: Programming Language :: Python :: 2.7
